["226ffdb43f200528670d7c812ef1bf20", {"date": "2021-05-08", "type": "fixture", "squad": "Manchester City", "image": "https://d2p3bygnnzw9w3.cloudfront.net/req/202011251/tlogo/fb/cff3d9bb.png", "answers": ["Chelsea", "Tottenham", "West Ham", "Crystal Palace"], "v": "4"}, {"date": "2021-05-08", "type": "fixture", "squad": "Chelsea", "image": "https://d2p3bygnnzw9w3.cloudfront.net/req/202011251/tlogo/fb/b8fd03ef.png", "answers": ["Manchester City", "Crystal Palace", "Everton", "Newcastle Utd"], "v": "4"}, {"date": "2021-05-08", "type": "finalscore", "squad_a": "Manchester City", "squad_b": "Chelsea", "image": "https://d2p3bygnnzw9w3.cloudfront.net/req/202011251/tlogo/fb/cff3d9bb.png", "answers": ["1\u20132", "3\u20131", "5\u20130", "2\u20130"], "v": "4"}, {"date": "2021-05-08", "type": "manager", "squad_a": "Manchester City", "squad_b": "Chelsea", "team": "Manchester City", "image": "https://d2p3bygnnzw9w3.cloudfront.net/req/202011251/tlogo/fb/b8fd03ef.png", "answers": ["Pep\u00a0Guardiola", "Scott\u00a0Parker", "Ryan\u00a0Mason", "David\u00a0Moyes"], "v": "8"}, {"date": "2021-05-08", "type": "manager", "squad_a": "Manchester City", "squad_b": "Chelsea", "team": "Chelsea", "image": "https://d2p3bygnnzw9w3.cloudfront.net/req/202011251/tlogo/fb/cff3d9bb.png", "answers": ["Thomas\u00a0Tuchel", "Steve\u00a0Bruce", "Mikel\u00a0Arteta", "David\u00a0Moyes"], "v": "8"}, {"date": "2021-05-08", "type": "captain", "squad_a": "Manchester City", "squad_b": "Chelsea", "team": "Manchester City", "image": "https://fbref.com/req/202005121/images/headshots/b400bde0_2018.jpg", "answers": ["Raheem\u00a0Sterling", "Michael\u00a0Keane", "Jamaal\u00a0Lascelles", "James\u00a0Milner"], "v": "8"}, {"date": "2021-05-08", "type": "captain", "squad_a": "Manchester City", "squad_b": "Chelsea", "team": "Chelsea", "image": "https://fbref.com/req/202005121/images/headshots/53cad200_2018.jpg", "answers": ["C\u00e9sar\u00a0Azpilicueta", "Lucas\u00a0Digne", "Hugo\u00a0Lloris", "Jordan\u00a0Henderson"], "v": "8"}, {"date": "2021-05-08", "type": "venue", "squad_a": "Manchester City", "squad_b": "Chelsea", "image": "https://d2p3bygnnzw9w3.cloudfront.net/req/202011251/tlogo/fb/b8fd03ef.png", "answers": ["Etihad Stadium", "Turf Moor", "Tottenham Hotspur Stadium", "Selhurst Park"], "v": "4"}, {"date": "2021-05-08", "type": "scorer", "squad_a": "Manchester City", "squad_b": "Chelsea", "minute": "44", "team": "Manchester City", "score": "1:0", "image": "https://fbref.com/req/202005121/images/headshots/b400bde0_2018.jpg", "answers": ["Raheem Sterling", "Ayoze P\u00e9rez", "\u00c9rik Lamela", "Adama Traor\u00e9"], "v": "4"}, {"date": "2021-05-08", "type": "scorer", "squad_a": "Manchester City", "squad_b": "Chelsea", "minute": "63", "team": "Chelsea", "score": "1:1", "image": "https://fbref.com/req/202005121/images/headshots/6622454d_2018.jpg", "answers": ["Hakim Ziyech", "Timothy Castagne", "Semi Ajayi", "Gabriel Dos Santos"], "v": "4"}, {"date": "2021-05-08", "type": "scorer", "squad_a": "Manchester City", "squad_b": "Chelsea", "minute": "92", "team": "Chelsea", "score": "1:2", "image": "https://fbref.com/req/202005121/images/headshots/f4290206_2018.jpg", "answers": ["Marcos Alonso", "Keinan Davis", "Jack Harrison", "Jordan Ayew"], "v": "4"}, {"date": "2021-05-08", "type": "fixture", "squad": "Sheffield Utd", "image": "https://d2p3bygnnzw9w3.cloudfront.net/req/202011251/tlogo/fb/47c64c55.png", "answers": ["Crystal Palace", "Southampton", "Manchester City", "Aston Villa"], "v": "4"}, {"date": "2021-05-08", "type": "fixture", "squad": "Crystal Palace", "image": "https://d2p3bygnnzw9w3.cloudfront.net/req/202011251/tlogo/fb/1df6b87e.png", "answers": ["Sheffield Utd", "Chelsea", "Leicester City", "Southampton"], "v": "4"}, {"date": "2021-05-08", "type": "finalscore", "squad_a": "Sheffield Utd", "squad_b": "Crystal Palace", "image": "https://d2p3bygnnzw9w3.cloudfront.net/req/202011251/tlogo/fb/47c64c55.png", "answers": ["0\u20132", "1\u20131", "5\u20132", "3\u20134"], "v": "4"}, {"date": "2021-05-08", "type": "manager", "squad_a": "Sheffield Utd", "squad_b": "Crystal Palace", "team": "Sheffield Utd", "image": "https://d2p3bygnnzw9w3.cloudfront.net/req/202011251/tlogo/fb/1df6b87e.png", "answers": ["Paul\u00a0Heckingbottom", "Roy\u00a0Hodgson", "Ryan\u00a0Mason", "Ole\u00a0Gunnar\u00a0Solskj\u00e6r"], "v": "8"}, {"date": "2021-05-08", "type": "manager", "squad_a": "Sheffield Utd", "squad_b": "Crystal Palace", "team": "Crystal Palace", "image": "https://d2p3bygnnzw9w3.cloudfront.net/req/202011251/tlogo/fb/47c64c55.png", "answers": ["Roy\u00a0Hodgson", "Ryan\u00a0Mason", "Graham\u00a0Potter", "Pep\u00a0Guardiola"], "v": "8"}, {"date": "2021-05-08", "type": "captain", "squad_a": "Sheffield Utd", "squad_b": "Crystal Palace", "team": "Sheffield Utd", "image": "https://fbref.com/req/202005121/images/headshots/debe38a0_2018.jpg", "answers": ["John\u00a0Egan", "Branislav\u00a0Ivanovi\u0107", "Matt\u00a0Phillips", "Jamaal\u00a0Lascelles"], "v": "8"}, {"date": "2021-05-08", "type": "captain", "squad_a": "Sheffield Utd", "squad_b": "Crystal Palace", "team": "Crystal Palace", "image": "https://fbref.com/req/202005121/images/headshots/2ce2508a_2018.jpg", "answers": ["Luka\u00a0Milivojevi\u0107", "Federico\u00a0Fern\u00e1ndez", "Jake\u00a0Livermore", "Wilfried\u00a0Zaha"], "v": "8"}, {"date": "2021-05-08", "type": "venue", "squad_a": "Sheffield Utd", "squad_b": "Crystal Palace", "image": "https://d2p3bygnnzw9w3.cloudfront.net/req/202011251/tlogo/fb/1df6b87e.png", "answers": ["Bramall Lane", "Emirates Stadium", "Selhurst Park", "Stamford Bridge"], "v": "4"}, {"date": "2021-05-08", "type": "scorer", "squad_a": "Sheffield Utd", "squad_b": "Crystal Palace", "minute": "2", "team": "Crystal Palace", "score": "0:1", "image": "https://fbref.com/req/202005121/images/headshots/ab070c55_2018.jpg", "answers": ["Christian Benteke", "Conor Coady", "Giovani Lo Celso", "Jonjo Shelvey"], "v": "4"}, {"date": "2021-05-08", "type": "scorer", "squad_a": "Sheffield Utd", "squad_b": "Crystal Palace", "minute": "88", "team": "Crystal Palace", "score": "0:2", "answers": ["Eberechi Eze", "Christian Benteke", "Raphael Dias Belloli", "Jayden Bogle"], "v": "4"}, {"date": "2021-05-09", "type": "fixture", "squad": "Arsenal", "image": "https://d2p3bygnnzw9w3.cloudfront.net/req/202011251/tlogo/fb/60c6b05f.png", "answers": ["West Brom", "Aston Villa", "Tottenham", "Crystal Palace"], "v": "4"}, {"date": "2021-05-09", "type": "fixture", "squad": "West Brom", "image": "https://d2p3bygnnzw9w3.cloudfront.net/req/202011251/tlogo/fb/18bb7c10.png", "answers": ["Arsenal", "Crystal Palace", "Sheffield Utd", "West Ham"], "v": "4"}, {"date": "2021-05-09", "type": "finalscore", "squad_a": "Arsenal", "squad_b": "West Brom", "image": "https://d2p3bygnnzw9w3.cloudfront.net/req/202011251/tlogo/fb/18bb7c10.png", "answers": ["3\u20131", "6\u20132", "4\u20133", "2\u20130"], "v": "4"}, {"date": "2021-05-09", "type": "manager", "squad_a": "Arsenal", "squad_b": "West Brom", "team": "Arsenal", "image": "https://d2p3bygnnzw9w3.cloudfront.net/req/202011251/tlogo/fb/18bb7c10.png", "answers": ["Mikel\u00a0Arteta", "Brendan\u00a0Rodgers", "Frank\u00a0Lampard", "Ralph\u00a0Hasenh\u00fcttl"], "v": "8"}, {"date": "2021-05-09", "type": "manager", "squad_a": "Arsenal", "squad_b": "West Brom", "team": "West Brom", "image": "https://d2p3bygnnzw9w3.cloudfront.net/req/202011251/tlogo/fb/60c6b05f.png", "answers": ["Sam\u00a0Allardyce", "Jos\u00e9\u00a0Mourinho", "Ralph\u00a0Hasenh\u00fcttl", "Frank\u00a0Lampard"], "v": "8"}, {"date": "2021-05-09", "type": "captain", "squad_a": "Arsenal", "squad_b": "West Brom", "team": "Arsenal", "image": "https://fbref.com/req/202005121/images/headshots/d79a8c87_2018.jpg", "answers": ["Rob\u00a0Holding", "Tyrone\u00a0Mings", "Mason\u00a0Holgate", "\u0130lkay\u00a0G\u00fcndo\u011fan"], "v": "8"}, {"date": "2021-05-09", "type": "captain", "squad_a": "Arsenal", "squad_b": "West Brom", "team": "West Brom", "image": "https://fbref.com/req/202005121/images/headshots/18e96f64_2018.jpg", "answers": ["Kyle\u00a0Bartley", "Jonjo\u00a0Shelvey", "Alexandre\u00a0Lacazette", "John\u00a0Egan"], "v": "8"}, {"date": "2021-05-09", "type": "venue", "squad_a": "Arsenal", "squad_b": "West Brom", "image": "https://d2p3bygnnzw9w3.cloudfront.net/req/202011251/tlogo/fb/18bb7c10.png", "answers": ["Emirates Stadium", "Craven Cottage", "Old Trafford", "Bramall Lane"], "v": "4"}, {"date": "2021-05-09", "type": "scorer", "squad_a": "Arsenal", "squad_b": "West Brom", "minute": "29", "team": "Arsenal", "score": "1:0", "image": "https://fbref.com/req/202005121/images/headshots/17695062_2018.jpg", "answers": ["Emile Smith-Rowe", "Timo Werner", "Gareth Bale", "Jo\u00ebl Matip"], "v": "4"}, {"date": "2021-05-09", "type": "scorer", "squad_a": "Arsenal", "squad_b": "West Brom", "minute": "35", "team": "Arsenal", "score": "2:0", "image": "https://fbref.com/req/202005121/images/headshots/57e3f0c7_2018.jpg", "answers": ["Nicolas P\u00e9p\u00e9", "N\u00e9lson Semedo", "Tariq Lamptey", "Luke Thomas"], "v": "4"}, {"date": "2021-05-09", "type": "scorer", "squad_a": "Arsenal", "squad_b": "West Brom", "minute": "67", "team": "West Brom", "score": "2:1", "image": "https://fbref.com/req/202005121/images/headshots/b04ee927_2018.jpg", "answers": ["Matheus Pereira", "Alexis Mac Allister", "Neal Maupay", "Jake Livermore"], "v": "4"}, {"date": "2021-05-09", "type": "scorer", "squad_a": "Arsenal", "squad_b": "West Brom", "minute": "90", "team": "Arsenal", "score": "3:1", "image": "https://fbref.com/req/202005121/images/headshots/8b9ebd03_2018.jpg", "answers": ["Willian", "Pablo Fornals", "Erik Pieters", "Daniel Podence"], "v": "4"}, {"date": "2021-05-09", "type": "fixture", "squad": "Aston Villa", "image": "https://d2p3bygnnzw9w3.cloudfront.net/req/202011251/tlogo/fb/19538871.png", "answers": ["Manchester Utd", "West Ham", "Everton", "Chelsea"], "v": "4"}, {"date": "2021-05-09", "type": "fixture", "squad": "Manchester Utd", "image": "https://d2p3bygnnzw9w3.cloudfront.net/req/202011251/tlogo/fb/8602292d.png", "answers": ["Aston Villa", "Tottenham", "Crystal Palace", "Liverpool"], "v": "4"}, {"date": "2021-05-09", "type": "finalscore", "squad_a": "Aston Villa", "squad_b": "Manchester Utd", "image": "https://d2p3bygnnzw9w3.cloudfront.net/req/202011251/tlogo/fb/19538871.png", "answers": ["1\u20133", "1\u20136", "2\u20131", "7\u20132"], "v": "4"}, {"date": "2021-05-09", "type": "manager", "squad_a": "Aston Villa", "squad_b": "Manchester Utd", "team": "Aston Villa", "image": "https://d2p3bygnnzw9w3.cloudfront.net/req/202011251/tlogo/fb/8602292d.png", "answers": ["Dean\u00a0Smith", "J\u00fcrgen\u00a0Klopp", "Marcelo\u00a0Bielsa", "Frank\u00a0Lampard"], "v": "8"}, {"date": "2021-05-09", "type": "manager", "squad_a": "Aston Villa", "squad_b": "Manchester Utd", "team": "Manchester Utd", "image": "https://d2p3bygnnzw9w3.cloudfront.net/req/202011251/tlogo/fb/19538871.png", "answers": ["Ole\u00a0Gunnar\u00a0Solskj\u00e6r", "Sean\u00a0Dyche", "Roy\u00a0Hodgson", "Mikel\u00a0Arteta"], "v": "8"}, {"date": "2021-05-09", "type": "captain", "squad_a": "Aston Villa", "squad_b": "Manchester Utd", "team": "Aston Villa", "image": "https://fbref.com/req/202005121/images/headshots/8397a50c_2018.jpg", "answers": ["Tyrone\u00a0Mings", "Fernandinho", "James\u00a0Milner", "Luke\u00a0Ayling"], "v": "8"}, {"date": "2021-05-09", "type": "captain", "squad_a": "Aston Villa", "squad_b": "Manchester Utd", "team": "Manchester Utd", "image": "https://fbref.com/req/202005121/images/headshots/d8931174_2018.jpg", "answers": ["Harry\u00a0Maguire", "James\u00a0Ward-Prowse", "James\u00a0Milner", "\u0130lkay\u00a0G\u00fcndo\u011fan"], "v": "8"}, {"date": "2021-05-09", "type": "venue", "squad_a": "Aston Villa", "squad_b": "Manchester Utd", "image": "https://d2p3bygnnzw9w3.cloudfront.net/req/202011251/tlogo/fb/8602292d.png", "answers": ["Villa Park", "Anfield", "Bramall Lane", "London Stadium"], "v": "4"}, {"date": "2021-05-09", "type": "scorer", "squad_a": "Aston Villa", "squad_b": "Manchester Utd", "minute": "24", "team": "Aston Villa", "score": "1:0", "image": "https://fbref.com/req/202005121/images/headshots/c47541e0_2018.jpg", "answers": ["Bertrand Traor\u00e9", "Paul Pogba", "Mbaye Diagne", "Oliver McBurnie"], "v": "4"}, {"date": "2021-05-09", "type": "scorer", "squad_a": "Aston Villa", "squad_b": "Manchester Utd", "minute": "52", "team": "Manchester Utd", "score": "1:1", "image": "https://fbref.com/req/202005121/images/headshots/507c7bdf_2018.jpg", "answers": ["Bruno Fernandes", "Pierre-Emerick Aubameyang", "Oliver McBurnie", "Conor Coady"], "v": "4"}, {"date": "2021-05-09", "type": "scorer", "squad_a": "Aston Villa", "squad_b": "Manchester Utd", "minute": "56", "team": "Manchester Utd", "score": "1:2", "image": "https://fbref.com/req/202005121/images/headshots/58eee997_2018.jpg", "answers": ["Mason Greenwood", "Joe Willock", "Willian Jos\u00e9", "Callum Wilson"], "v": "4"}, {"date": "2021-05-09", "type": "scorer", "squad_a": "Aston Villa", "squad_b": "Manchester Utd", "minute": "87", "team": "Manchester Utd", "score": "1:3", "image": "https://fbref.com/req/202005121/images/headshots/527f063d_2018.jpg", "answers": ["Edinson Cavani", "Ayoze P\u00e9rez", "Jo\u00e3o Cancelo", "Solly March"], "v": "4"}, {"date": "2021-05-09", "type": "red", "squad_a": "Aston Villa", "squad_b": "Manchester Utd", "minute": "89", "team": "Aston Villa", "score": "1:3", "image": "https://fbref.com/req/202005121/images/headshots/aed3a70f_2018.jpg", "answers": ["Ollie Watkins", "Luka Milivojevi\u0107", "Tariq Lamptey", "Maxime Le Marchand"], "v": "4"}, {"date": "2021-05-09", "type": "fixture", "squad": "West Ham", "image": "https://d2p3bygnnzw9w3.cloudfront.net/req/202011251/tlogo/fb/d3fd31cc.png", "answers": ["Everton", "Manchester Utd", "Leicester City", "Burnley"], "v": "4"}, {"date": "2021-05-09", "type": "fixture", "squad": "Everton", "image": "https://d2p3bygnnzw9w3.cloudfront.net/req/202011251/tlogo/fb/7c21e445.png", "answers": ["West Ham", "Manchester City", "Leicester City", "Newcastle Utd"], "v": "4"}, {"date": "2021-05-09", "type": "finalscore", "squad_a": "West Ham", "squad_b": "Everton", "image": "https://d2p3bygnnzw9w3.cloudfront.net/req/202011251/tlogo/fb/d3fd31cc.png", "answers": ["0\u20131", "2\u20131", "0\u20133", "2\u20130"], "v": "4"}, {"date": "2021-05-09", "type": "manager", "squad_a": "West Ham", "squad_b": "Everton", "team": "West Ham", "image": "https://d2p3bygnnzw9w3.cloudfront.net/req/202011251/tlogo/fb/7c21e445.png", "answers": ["David\u00a0Moyes", "Jos\u00e9\u00a0Mourinho", "Paul\u00a0Heckingbottom", "Ralph\u00a0Hasenh\u00fcttl"], "v": "8"}, {"date": "2021-05-09", "type": "manager", "squad_a": "West Ham", "squad_b": "Everton", "team": "Everton", "image": "https://d2p3bygnnzw9w3.cloudfront.net/req/202011251/tlogo/fb/d3fd31cc.png", "answers": ["Carlo\u00a0Ancelotti", "Paul\u00a0Heckingbottom", "Frank\u00a0Lampard", "Sam\u00a0Allardyce"], "v": "8"}, {"date": "2021-05-09", "type": "captain", "squad_a": "West Ham", "squad_b": "Everton", "team": "West Ham", "image": "https://fbref.com/req/202005121/images/headshots/4f974391_2018.jpg", "answers": ["Aaron\u00a0Cresswell", "Kyle\u00a0Bartley", "Conor\u00a0Coady", "Mason\u00a0Holgate"], "v": "8"}, {"date": "2021-05-09", "type": "captain", "squad_a": "West Ham", "squad_b": "Everton", "team": "Everton", "image": "https://fbref.com/req/202005121/images/headshots/0420d84f_2018.jpg", "answers": ["S\u00e9amus\u00a0Coleman", "\u0130lkay\u00a0G\u00fcndo\u011fan", "Kasper\u00a0Schmeichel", "Jamaal\u00a0Lascelles"], "v": "8"}, {"date": "2021-05-09", "type": "venue", "squad_a": "West Ham", "squad_b": "Everton", "image": "https://d2p3bygnnzw9w3.cloudfront.net/req/202011251/tlogo/fb/7c21e445.png", "answers": ["London Stadium", "The American Express Community Stadium", "St. James' Park", "Anfield"], "v": "4"}, {"date": "2021-05-09", "type": "scorer", "squad_a": "West Ham", "squad_b": "Everton", "minute": "24", "team": "Everton", "score": "0:1", "image": "https://fbref.com/req/202005121/images/headshots/59e6e5bf_2018.jpg", "answers": ["Dominic Calvert-Lewin", "N\u00e9lson Semedo", "James Maddison", "Jacob Murphy"], "v": "4"}, {"date": "2021-05-09", "type": "fixture", "squad": "Wolves", "image": "https://d2p3bygnnzw9w3.cloudfront.net/req/202011251/tlogo/fb/d07537b9.png", "answers": ["Brighton", "Aston Villa", "West Ham", "Manchester Utd"], "v": "4"}, {"date": "2021-05-09", "type": "fixture", "squad": "Brighton", "image": "https://d2p3bygnnzw9w3.cloudfront.net/req/202011251/tlogo/fb/8cec06e1.png", "answers": ["Wolves", "Fulham", "West Ham", "Tottenham"], "v": "4"}, {"date": "2021-05-09", "type": "finalscore", "squad_a": "Wolves", "squad_b": "Brighton", "image": "https://d2p3bygnnzw9w3.cloudfront.net/req/202011251/tlogo/fb/8cec06e1.png", "answers": ["2\u20131", "6\u20132", "1\u20135", "0\u20137"], "v": "4"}, {"date": "2021-05-09", "type": "manager", "squad_a": "Wolves", "squad_b": "Brighton", "team": "Wolves", "image": "https://d2p3bygnnzw9w3.cloudfront.net/req/202011251/tlogo/fb/8cec06e1.png", "answers": ["Nuno\u00a0Esp\u00edrito\u00a0Santo", "Ole\u00a0Gunnar\u00a0Solskj\u00e6r", "Mikel\u00a0Arteta", "Graham\u00a0Potter"], "v": "8"}, {"date": "2021-05-09", "type": "manager", "squad_a": "Wolves", "squad_b": "Brighton", "team": "Brighton", "image": "https://d2p3bygnnzw9w3.cloudfront.net/req/202011251/tlogo/fb/d07537b9.png", "answers": ["Graham\u00a0Potter", "Pep\u00a0Guardiola", "Steve\u00a0Bruce", "Brendan\u00a0Rodgers"], "v": "8"}, {"date": "2021-05-09", "type": "captain", "squad_a": "Wolves", "squad_b": "Brighton", "team": "Wolves", "image": "https://fbref.com/req/202005121/images/headshots/2928dca2_2018.jpg", "answers": ["Conor\u00a0Coady", "Tyrone\u00a0Mings", "Kyle\u00a0Bartley", "Adam\u00a0Webster"], "v": "8"}, {"date": "2021-05-09", "type": "captain", "squad_a": "Wolves", "squad_b": "Brighton", "team": "Brighton", "image": "https://fbref.com/req/202005121/images/headshots/282f75f3_2018.jpg", "answers": ["Lewis\u00a0Dunk", "Kyle\u00a0Bartley", "Joachim\u00a0Andersen", "James\u00a0Milner"], "v": "8"}, {"date": "2021-05-09", "type": "venue", "squad_a": "Wolves", "squad_b": "Brighton", "image": "https://d2p3bygnnzw9w3.cloudfront.net/req/202011251/tlogo/fb/8cec06e1.png", "answers": ["Molineux Stadium", "Craven Cottage", "Tottenham Hotspur Stadium", "Bramall Lane"], "v": "4"}, {"date": "2021-05-09", "type": "scorer", "squad_a": "Wolves", "squad_b": "Brighton", "minute": "13", "team": "Brighton", "score": "0:1", "image": "https://fbref.com/req/202005121/images/headshots/282f75f3_2018.jpg", "answers": ["Lewis Dunk", "Leandro Trossard", "Ra\u00fal Jim\u00e9nez", "Ezgjan Alioski"], "v": "4"}, {"date": "2021-05-09", "type": "red", "squad_a": "Wolves", "squad_b": "Brighton", "minute": "53", "team": "Brighton", "score": "0:1", "image": "https://fbref.com/req/202005121/images/headshots/282f75f3_2018.jpg", "answers": ["Lewis Dunk", "Miguel Almir\u00f3n", "Oliver Burke", "Antonee Robinson"], "v": "4"}, {"date": "2021-05-09", "type": "scorer", "squad_a": "Wolves", "squad_b": "Brighton", "minute": "76", "team": "Wolves", "score": "1:1", "image": "https://fbref.com/req/202005121/images/headshots/9a28eba4_2018.jpg", "answers": ["Adama Traor\u00e9", "Jamaal Lascelles", "Neal Maupay", "Morgan Gibbs-White"], "v": "4"}, {"date": "2021-05-09", "type": "scorer", "squad_a": "Wolves", "squad_b": "Brighton", "minute": "90", "team": "Wolves", "score": "2:1", "image": "https://fbref.com/req/202005121/images/headshots/32f60ed8_2018.jpg", "answers": ["Morgan Gibbs-White", "\u00c7a\u011flar S\u00f6y\u00fcnc\u00fc", "Rob Holding", "Kortney Hause"], "v": "4"}, {"date": "2021-05-09", "type": "red", "squad_a": "Wolves", "squad_b": "Brighton", "minute": "97", "team": "Brighton", "score": "2:1", "image": "https://fbref.com/req/202005121/images/headshots/4bcf39f6_2018.jpg", "answers": ["Neal Maupay", "Ederson", "James Ward-Prowse", "Conor Gallagher"], "v": "4"}, {"date": "2021-05-10", "type": "fixture", "squad": "Fulham", "image": "https://d2p3bygnnzw9w3.cloudfront.net/req/202011251/tlogo/fb/943e8050.png", "answers": ["Burnley", "Brighton", "Manchester Utd", "West Ham"], "v": "4"}, {"date": "2021-05-10", "type": "fixture", "squad": "Burnley", "image": "https://d2p3bygnnzw9w3.cloudfront.net/req/202011251/tlogo/fb/fd962109.png", "answers": ["Fulham", "Arsenal", "Everton", "Chelsea"], "v": "4"}, {"date": "2021-05-10", "type": "finalscore", "squad_a": "Fulham", "squad_b": "Burnley", "image": "https://d2p3bygnnzw9w3.cloudfront.net/req/202011251/tlogo/fb/943e8050.png", "answers": ["0\u20132", "2\u20133", "0\u20133", "2\u20135"], "v": "4"}, {"date": "2021-05-10", "type": "manager", "squad_a": "Fulham", "squad_b": "Burnley", "team": "Fulham", "image": "https://d2p3bygnnzw9w3.cloudfront.net/req/202011251/tlogo/fb/fd962109.png", "answers": ["Scott\u00a0Parker", "Pep\u00a0Guardiola", "Jos\u00e9\u00a0Mourinho", "Carlo\u00a0Ancelotti"], "v": "8"}, {"date": "2021-05-10", "type": "manager", "squad_a": "Fulham", "squad_b": "Burnley", "team": "Burnley", "image": "https://d2p3bygnnzw9w3.cloudfront.net/req/202011251/tlogo/fb/943e8050.png", "answers": ["Sean\u00a0Dyche", "Pep\u00a0Guardiola", "Dean\u00a0Smith", "Brendan\u00a0Rodgers"], "v": "8"}, {"date": "2021-05-10", "type": "captain", "squad_a": "Fulham", "squad_b": "Burnley", "team": "Fulham", "image": "https://fbref.com/req/202005121/images/headshots/e34fc66d_2018.jpg", "answers": ["Joachim\u00a0Andersen", "Jake\u00a0Livermore", "Georginio\u00a0Wijnaldum", "James\u00a0Milner"], "v": "8"}, {"date": "2021-05-10", "type": "captain", "squad_a": "Fulham", "squad_b": "Burnley", "team": "Burnley", "image": "https://fbref.com/req/202005121/images/headshots/8df7a2fb_2018.jpg", "answers": ["Ben\u00a0Mee", "David\u00a0McGoldrick", "Gylfi\u00a0Sigur\u00f0sson", "Jordan\u00a0Henderson"], "v": "8"}, {"date": "2021-05-10", "type": "venue", "squad_a": "Fulham", "squad_b": "Burnley", "image": "https://d2p3bygnnzw9w3.cloudfront.net/req/202011251/tlogo/fb/fd962109.png", "answers": ["Craven Cottage", "Tottenham Hotspur Stadium", "Etihad Stadium", "Anfield"], "v": "4"}, {"date": "2021-05-10", "type": "scorer", "squad_a": "Fulham", "squad_b": "Burnley", "minute": "35", "team": "Burnley", "score": "0:1", "image": "https://fbref.com/req/202005121/images/headshots/495945ef_2018.jpg", "answers": ["Ashley Westwood", "Dwight McNeil", "Ciaran Clark", "Neal Maupay"], "v": "4"}, {"date": "2021-05-10", "type": "scorer", "squad_a": "Fulham", "squad_b": "Burnley", "minute": "44", "team": "Burnley", "score": "0:2", "image": "https://fbref.com/req/202005121/images/headshots/4e9a0555_2018.jpg", "answers": ["Chris Wood", "Riyad Mahrez", "Declan Rice", "Granit Xhaka"], "v": "4"}, {"date": "2021-05-11", "type": "fixture", "squad": "Manchester Utd", "image": "https://d2p3bygnnzw9w3.cloudfront.net/req/202011251/tlogo/fb/a2d435b3.png", "answers": ["Leicester City", "Everton", "Sheffield Utd", "Crystal Palace"], "v": "4"}, {"date": "2021-05-11", "type": "fixture", "squad": "Leicester City", "image": "https://d2p3bygnnzw9w3.cloudfront.net/req/202011251/tlogo/fb/19538871.png", "answers": ["Manchester Utd", "Leeds United", "Sheffield Utd", "Wolves"], "v": "4"}, {"date": "2021-05-11", "type": "finalscore", "squad_a": "Manchester Utd", "squad_b": "Leicester City", "image": "https://d2p3bygnnzw9w3.cloudfront.net/req/202011251/tlogo/fb/a2d435b3.png", "answers": ["1\u20132", "5\u20130", "0\u20131", "1\u20136"], "v": "4"}, {"date": "2021-05-11", "type": "manager", "squad_a": "Manchester Utd", "squad_b": "Leicester City", "team": "Manchester Utd", "image": "https://d2p3bygnnzw9w3.cloudfront.net/req/202011251/tlogo/fb/19538871.png", "answers": ["Ole\u00a0Gunnar\u00a0Solskj\u00e6r", "Carlo\u00a0Ancelotti", "Nuno\u00a0Esp\u00edrito\u00a0Santo", "Roy\u00a0Hodgson"], "v": "8"}, {"date": "2021-05-11", "type": "manager", "squad_a": "Manchester Utd", "squad_b": "Leicester City", "team": "Leicester City", "image": "https://d2p3bygnnzw9w3.cloudfront.net/req/202011251/tlogo/fb/a2d435b3.png", "answers": ["Brendan\u00a0Rodgers", "Sam\u00a0Allardyce", "Steve\u00a0Bruce", "Mikel\u00a0Arteta"], "v": "8"}, {"date": "2021-05-11", "type": "captain", "squad_a": "Manchester Utd", "squad_b": "Leicester City", "team": "Manchester Utd", "image": "https://fbref.com/req/202005121/images/headshots/eb7822d7_2018.jpg", "answers": ["Nemanja\u00a0Mati\u0107", "Rob\u00a0Holding", "R\u00faben\u00a0Neves", "\u0130lkay\u00a0G\u00fcndo\u011fan"], "v": "8"}, {"date": "2021-05-11", "type": "captain", "squad_a": "Manchester Utd", "squad_b": "Leicester City", "team": "Leicester City", "image": "https://d2p3bygnnzw9w3.cloudfront.net/req/202011251/tlogo/fb/a2d435b3.png", "answers": ["Kasper\u00a0Schmeichel", "Jamaal\u00a0Lascelles", "Declan\u00a0Rice", "Scott\u00a0Dann"], "v": "8"}, {"date": "2021-05-11", "type": "venue", "squad_a": "Manchester Utd", "squad_b": "Leicester City", "image": "https://d2p3bygnnzw9w3.cloudfront.net/req/202011251/tlogo/fb/19538871.png", "answers": ["Old Trafford", "Emirates Stadium", "Selhurst Park", "Etihad Stadium"], "v": "4"}, {"date": "2021-05-11", "type": "scorer", "squad_a": "Manchester Utd", "squad_b": "Leicester City", "minute": "10", "team": "Leicester City", "score": "0:1", "answers": ["Luke Thomas", "H\u00e9lder Costa", "Raheem Sterling", "Daniel James"], "v": "4"}, {"date": "2021-05-11", "type": "scorer", "squad_a": "Manchester Utd", "squad_b": "Leicester City", "minute": "15", "team": "Manchester Utd", "score": "1:1", "image": "https://fbref.com/req/202005121/images/headshots/58eee997_2018.jpg", "answers": ["Mason Greenwood", "Leander Dendoncker", "Rob Holding", "Semi Ajayi"], "v": "4"}, {"date": "2021-05-11", "type": "scorer", "squad_a": "Manchester Utd", "squad_b": "Leicester City", "minute": "66", "team": "Leicester City", "score": "1:2", "image": "https://fbref.com/req/202005121/images/headshots/21166ff4_2018.jpg", "answers": ["\u00c7a\u011flar S\u00f6y\u00fcnc\u00fc", "Luke Shaw", "Ruben Loftus-Cheek", "Ola Aina"], "v": "4"}, {"date": "2021-05-11", "type": "fixture", "squad": "Southampton", "image": "https://d2p3bygnnzw9w3.cloudfront.net/req/202011251/tlogo/fb/47c64c55.png", "answers": ["Crystal Palace", "Leeds United", "Wolves", "Fulham"], "v": "4"}, {"date": "2021-05-11", "type": "fixture", "squad": "Crystal Palace", "image": "https://d2p3bygnnzw9w3.cloudfront.net/req/202011251/tlogo/fb/33c895d4.png", "answers": ["Southampton", "Tottenham", "Everton", "Sheffield Utd"], "v": "4"}, {"date": "2021-05-11", "type": "finalscore", "squad_a": "Southampton", "squad_b": "Crystal Palace", "image": "https://d2p3bygnnzw9w3.cloudfront.net/req/202011251/tlogo/fb/33c895d4.png", "answers": ["3\u20131", "3\u20130", "2\u20132", "0\u20134"], "v": "4"}, {"date": "2021-05-11", "type": "manager", "squad_a": "Southampton", "squad_b": "Crystal Palace", "team": "Southampton", "image": "https://d2p3bygnnzw9w3.cloudfront.net/req/202011251/tlogo/fb/33c895d4.png", "answers": ["Ralph\u00a0Hasenh\u00fcttl", "Jos\u00e9\u00a0Mourinho", "Steve\u00a0Bruce", "Dean\u00a0Smith"], "v": "8"}, {"date": "2021-05-11", "type": "manager", "squad_a": "Southampton", "squad_b": "Crystal Palace", "team": "Crystal Palace", "image": "https://d2p3bygnnzw9w3.cloudfront.net/req/202011251/tlogo/fb/47c64c55.png", "answers": ["Roy\u00a0Hodgson", "Nuno\u00a0Esp\u00edrito\u00a0Santo", "Frank\u00a0Lampard", "Paul\u00a0Heckingbottom"], "v": "8"}, {"date": "2021-05-11", "type": "captain", "squad_a": "Southampton", "squad_b": "Crystal Palace", "team": "Southampton", "image": "https://fbref.com/req/202005121/images/headshots/3515d404_2018.jpg", "answers": ["James\u00a0Ward-Prowse", "Scott\u00a0Dann", "Adam\u00a0Webster", "Tom\u00a0Cairney"], "v": "8"}, {"date": "2021-05-11", "type": "captain", "squad_a": "Southampton", "squad_b": "Crystal Palace", "team": "Crystal Palace", "image": "https://fbref.com/req/202005121/images/headshots/2ce2508a_2018.jpg", "answers": ["Luka\u00a0Milivojevi\u0107", "Billy\u00a0Sharp", "C\u00e9sar\u00a0Azpilicueta", "Harry\u00a0Kane"], "v": "8"}, {"date": "2021-05-11", "type": "venue", "squad_a": "Southampton", "squad_b": "Crystal Palace", "image": "https://d2p3bygnnzw9w3.cloudfront.net/req/202011251/tlogo/fb/33c895d4.png", "answers": ["St. Mary's Stadium", "St. James' Park", "Goodison Park", "London Stadium"], "v": "4"}, {"date": "2021-05-11", "type": "scorer", "squad_a": "Southampton", "squad_b": "Crystal Palace", "minute": "2", "team": "Crystal Palace", "score": "0:1", "image": "https://fbref.com/req/202005121/images/headshots/ab070c55_2018.jpg", "answers": ["Christian Benteke", "Victor Lindel\u00f6f", "Leandro Trossard", "Wilfred Ndidi"], "v": "4"}, {"date": "2021-05-11", "type": "scorer", "squad_a": "Southampton", "squad_b": "Crystal Palace", "minute": "19", "team": "Southampton", "score": "1:1", "image": "https://fbref.com/req/202005121/images/headshots/07802f7f_2018.jpg", "answers": ["Danny Ings", "Phil Jagielka", "Diogo Jota", "Raheem Sterling"], "v": "4"}, {"date": "2021-05-11", "type": "scorer", "squad_a": "Southampton", "squad_b": "Crystal Palace", "minute": "48", "team": "Southampton", "score": "2:1", "image": "https://fbref.com/req/202005121/images/headshots/f2bf1b0f_2018.jpg", "answers": ["Che Adams", "Toby Alderweireld", "Donny van de Beek", "Rob Holding"], "v": "4"}, {"date": "2021-05-11", "type": "scorer", "squad_a": "Southampton", "squad_b": "Crystal Palace", "minute": "75", "team": "Southampton", "score": "3:1", "image": "https://fbref.com/req/202005121/images/headshots/07802f7f_2018.jpg", "answers": ["Danny Ings", "H\u00e9lder Costa", "Daniel James", "Conor Coady"], "v": "4"}, {"date": "2021-05-12", "type": "fixture", "squad": "Chelsea", "image": "https://d2p3bygnnzw9w3.cloudfront.net/req/202011251/tlogo/fb/18bb7c10.png", "answers": ["Arsenal", "Southampton", "Fulham", "West Ham"], "v": "4"}, {"date": "2021-05-12", "type": "fixture", "squad": "Arsenal", "image": "https://d2p3bygnnzw9w3.cloudfront.net/req/202011251/tlogo/fb/cff3d9bb.png", "answers": ["Chelsea", "Sheffield Utd", "Crystal Palace", "Manchester Utd"], "v": "4"}, {"date": "2021-05-12", "type": "finalscore", "squad_a": "Chelsea", "squad_b": "Arsenal", "image": "https://d2p3bygnnzw9w3.cloudfront.net/req/202011251/tlogo/fb/18bb7c10.png", "answers": ["0\u20131", "1\u20132", "2\u20135", "5\u20130"], "v": "4"}, {"date": "2021-05-12", "type": "manager", "squad_a": "Chelsea", "squad_b": "Arsenal", "team": "Chelsea", "image": "https://d2p3bygnnzw9w3.cloudfront.net/req/202011251/tlogo/fb/cff3d9bb.png", "answers": ["Thomas\u00a0Tuchel", "Pep\u00a0Guardiola", "Sean\u00a0Dyche", "Brendan\u00a0Rodgers"], "v": "8"}, {"date": "2021-05-12", "type": "manager", "squad_a": "Chelsea", "squad_b": "Arsenal", "team": "Arsenal", "image": "https://d2p3bygnnzw9w3.cloudfront.net/req/202011251/tlogo/fb/18bb7c10.png", "answers": ["Mikel\u00a0Arteta", "Paul\u00a0Heckingbottom", "Ryan\u00a0Mason", "Marcelo\u00a0Bielsa"], "v": "8"}, {"date": "2021-05-12", "type": "captain", "squad_a": "Chelsea", "squad_b": "Arsenal", "team": "Chelsea", "image": "https://fbref.com/req/202005121/images/headshots/53cad200_2018.jpg", "answers": ["C\u00e9sar\u00a0Azpilicueta", "David\u00a0McGoldrick", "Rob\u00a0Holding", "Matt\u00a0Phillips"], "v": "8"}, {"date": "2021-05-12", "type": "captain", "squad_a": "Chelsea", "squad_b": "Arsenal", "team": "Arsenal", "image": "https://fbref.com/req/202005121/images/headshots/d5dd5f1f_2018.jpg", "answers": ["Pierre-Emerick\u00a0Aubameyang", "Billy\u00a0Sharp", "Kevin\u00a0De\u00a0Bruyne", "Thiago\u00a0Silva"], "v": "8"}, {"date": "2021-05-12", "type": "venue", "squad_a": "Chelsea", "squad_b": "Arsenal", "image": "https://d2p3bygnnzw9w3.cloudfront.net/req/202011251/tlogo/fb/cff3d9bb.png", "answers": ["Stamford Bridge", "Etihad Stadium", "Emirates Stadium", "London Stadium"], "v": "4"}, {"date": "2021-05-12", "type": "scorer", "squad_a": "Chelsea", "squad_b": "Arsenal", "minute": "16", "team": "Arsenal", "score": "0:1", "image": "https://fbref.com/req/202005121/images/headshots/17695062_2018.jpg", "answers": ["Emile Smith-Rowe", "Liam Cooper", "Jarrod Bowen", "Tanguy Ndombele"], "v": "4"}, {"date": "2021-05-12", "type": "top", "position": "1", "goals": "21", "image": "https://fbref.com/req/202005121/images/headshots/21a66f6a_2018.jpg", "answers": ["Harry Kane", "Timo Werner", "Jo\u00e3o Cancelo", "Ciaran Clark"], "v": "4"}, {"date": "2021-05-12", "type": "who", "position": "2", "goals": "20", "image": "https://fbref.com/req/202005121/images/headshots/e342ad68_2018.jpg", "answers": ["Mohamed Salah", "Jamie Vardy", "Willian", "Josh Maja"], "v": "4"}, {"date": "2021-05-12", "type": "who", "position": "3", "goals": "17", "image": "https://fbref.com/req/202005121/images/headshots/92e7e919_2018.jpg", "answers": ["Son Heung-min", "Andros Townsend", "Richarlison", "Bukayo Saka"], "v": "4"}, {"date": "2021-05-12", "type": "who", "position": "4", "goals": "17", "image": "https://fbref.com/req/202005121/images/headshots/507c7bdf_2018.jpg", "answers": ["Bruno Fernandes", "Ezgjan Alioski", "Martin \u00d8degaard", "Gabriel Jesus"], "v": "4"}, {"date": "2021-05-12", "type": "who", "position": "5", "goals": "16", "image": "https://fbref.com/req/202005121/images/headshots/59e6e5bf_2018.jpg", "answers": ["Dominic Calvert-Lewin", "Ademola Lookman", "Leandro Trossard", "Trent Alexander-Arnold"], "v": "4"}, {"date": "2021-05-12", "type": "who", "position": "6", "goals": "15", "image": "https://fbref.com/req/202005121/images/headshots/93feac6e_2018.jpg", "answers": ["Patrick Bamford", "Martin \u00d8degaard", "Dwight McNeil", "Callum Hudson-Odoi"], "v": "4"}, {"date": "2021-05-12", "type": "who", "position": "7", "goals": "13", "image": "https://fbref.com/req/202005121/images/headshots/9dbb75ca_2018.jpg", "answers": ["Alexandre Lacazette", "Scott McTominay", "Kean Bryan", "Mateusz Klich"], "v": "4"}, {"date": "2021-05-12", "type": "who", "position": "8", "goals": "13", "image": "https://fbref.com/req/202005121/images/headshots/45963054_2018.jpg", "answers": ["Jamie Vardy", "Stuart Dallas", "Toby Alderweireld", "Joe Willock"], "v": "4"}, {"date": "2021-05-12", "type": "who", "position": "9", "goals": "13", "image": "https://fbref.com/req/202005121/images/headshots/aed3a70f_2018.jpg", "answers": ["Ollie Watkins", "Jan Bednarek", "Jamaal Lascelles", "Jeff Hendrick"], "v": "4"}, {"date": "2021-05-12", "type": "who", "position": "10", "goals": "12", "image": "https://fbref.com/req/202005121/images/headshots/c596fcb0_2018.jpg", "answers": ["Callum Wilson", "Edinson Cavani", "Timo Werner", "Wilfred Ndidi"], "v": "4"}, {"date": "2021-05-12", "type": "table", "points": "80", "position": "1", "image": "https://d2p3bygnnzw9w3.cloudfront.net/req/202011251/tlogo/fb/b8fd03ef.png", "answers": ["Manchester City", "West Ham", "Sheffield Utd", "West Brom"], "v": "4"}, {"date": "2021-05-12", "type": "table", "points": "70", "position": "2", "image": "https://d2p3bygnnzw9w3.cloudfront.net/req/202011251/tlogo/fb/19538871.png", "answers": ["Manchester Utd", "Everton", "Wolves", "Leeds United"], "v": "4"}, {"date": "2021-05-12", "type": "table", "points": "66", "position": "3", "image": "https://d2p3bygnnzw9w3.cloudfront.net/req/202011251/tlogo/fb/a2d435b3.png", "answers": ["Leicester City", "Wolves", "Burnley", "Tottenham"], "v": "4"}, {"date": "2021-05-12", "type": "table", "points": "64", "position": "4", "image": "https://d2p3bygnnzw9w3.cloudfront.net/req/202011251/tlogo/fb/cff3d9bb.png", "answers": ["Chelsea", "West Ham", "Manchester City", "Tottenham"], "v": "4"}, {"date": "2021-05-12", "type": "table", "points": "58", "position": "5", "image": "https://d2p3bygnnzw9w3.cloudfront.net/req/202011251/tlogo/fb/7c21e445.png", "answers": ["West Ham", "Chelsea", "Arsenal", "Crystal Palace"], "v": "4"}, {"date": "2021-05-12", "type": "table", "points": "57", "position": "6", "image": "https://d2p3bygnnzw9w3.cloudfront.net/req/202011251/tlogo/fb/822bd0ba.png", "answers": ["Liverpool", "Southampton", "Chelsea", "Crystal Palace"], "v": "4"}, {"date": "2021-05-12", "type": "table", "points": "56", "position": "7", "image": "https://d2p3bygnnzw9w3.cloudfront.net/req/202011251/tlogo/fb/361ca564.png", "answers": ["Tottenham", "West Brom", "Brighton", "Manchester City"], "v": "4"}, {"date": "2021-05-12", "type": "table", "points": "55", "position": "8", "image": "https://d2p3bygnnzw9w3.cloudfront.net/req/202011251/tlogo/fb/18bb7c10.png", "answers": ["Arsenal", "Burnley", "West Ham", "Manchester Utd"], "v": "4"}, {"date": "2021-05-12", "type": "table", "points": "55", "position": "9", "image": "https://d2p3bygnnzw9w3.cloudfront.net/req/202011251/tlogo/fb/d3fd31cc.png", "answers": ["Everton", "Arsenal", "Burnley", "West Ham"], "v": "4"}, {"date": "2021-05-12", "type": "table", "points": "50", "position": "10", "image": "https://d2p3bygnnzw9w3.cloudfront.net/req/202011251/tlogo/fb/5bfb9659.png", "answers": ["Leeds United", "Brighton", "Arsenal", "Crystal Palace"], "v": "4"}, {"date": "2021-05-12", "type": "table", "points": "48", "position": "11", "image": "https://d2p3bygnnzw9w3.cloudfront.net/req/202011251/tlogo/fb/8602292d.png", "answers": ["Aston Villa", "Southampton", "Leicester City", "Tottenham"], "v": "4"}, {"date": "2021-05-12", "type": "table", "points": "45", "position": "12", "image": "https://d2p3bygnnzw9w3.cloudfront.net/req/202011251/tlogo/fb/8cec06e1.png", "answers": ["Wolves", "Crystal Palace", "Fulham", "Burnley"], "v": "4"}, {"date": "2021-05-12", "type": "table", "points": "41", "position": "13", "image": "https://d2p3bygnnzw9w3.cloudfront.net/req/202011251/tlogo/fb/47c64c55.png", "answers": ["Crystal Palace", "Everton", "Chelsea", "Arsenal"], "v": "4"}, {"date": "2021-05-12", "type": "table", "points": "40", "position": "14", "image": "https://d2p3bygnnzw9w3.cloudfront.net/req/202011251/tlogo/fb/33c895d4.png", "answers": ["Southampton", "Liverpool", "Newcastle Utd", "Arsenal"], "v": "4"}, {"date": "2021-05-12", "type": "table", "points": "39", "position": "15", "image": "https://d2p3bygnnzw9w3.cloudfront.net/req/202011251/tlogo/fb/943e8050.png", "answers": ["Burnley", "Manchester Utd", "West Ham", "Fulham"], "v": "4"}, {"date": "2021-05-12", "type": "table", "points": "39", "position": "16", "image": "https://d2p3bygnnzw9w3.cloudfront.net/req/202011251/tlogo/fb/b2b47a98.png", "answers": ["Newcastle Utd", "Burnley", "Aston Villa", "Everton"], "v": "4"}, {"date": "2021-05-12", "type": "table", "points": "37", "position": "17", "image": "https://d2p3bygnnzw9w3.cloudfront.net/req/202011251/tlogo/fb/d07537b9.png", "answers": ["Brighton", "Wolves", "Tottenham", "West Ham"], "v": "4"}, {"date": "2021-05-12", "type": "table", "points": "27", "position": "18", "image": "https://d2p3bygnnzw9w3.cloudfront.net/req/202011251/tlogo/fb/fd962109.png", "answers": ["Fulham", "Southampton", "Wolves", "Sheffield Utd"], "v": "4"}, {"date": "2021-05-12", "type": "table", "points": "26", "position": "19", "image": "https://d2p3bygnnzw9w3.cloudfront.net/req/202011251/tlogo/fb/60c6b05f.png", "answers": ["West Brom", "Leeds United", "Crystal Palace", "Liverpool"], "v": "4"}, {"date": "2021-05-12", "type": "table", "points": "17", "position": "20", "image": "https://d2p3bygnnzw9w3.cloudfront.net/req/202011251/tlogo/fb/1df6b87e.png", "answers": ["Sheffield Utd", "West Ham", "Burnley", "Southampton"], "v": "4"}, {"date": "2021-05-12", "type": "topassist", "position": "1", "assists": "13", "image": "https://fbref.com/req/202005121/images/headshots/21a66f6a_2018.jpg", "answers": ["Harry Kane", "Dwight Gayle", "James Ward-Prowse", "Michail Antonio"], "v": "17"}, {"date": "2021-05-12", "type": "whoassist", "position": "2", "assists": "11", "image": "https://fbref.com/req/202005121/images/headshots/e46012d4_2018.jpg", "answers": ["Kevin De Bruyne", "Kenny Tete", "Danny Welbeck", "Kalvin Phillips"], "v": "17"}, {"date": "2021-05-12", "type": "whoassist", "position": "3", "assists": "11", "image": "https://fbref.com/req/202005121/images/headshots/507c7bdf_2018.jpg", "answers": ["Bruno Fernandes", "Oliver Burke", "Ola Aina", "Conor Townsend"], "v": "17"}, {"date": "2021-05-12", "type": "whoassist", "position": "4", "assists": "10", "image": "https://fbref.com/req/202005121/images/headshots/92e7e919_2018.jpg", "answers": ["Son Heung-min", "Curtis Jones", "Tammy Abraham", "Daniel Podence"], "v": "17"}, {"date": "2021-05-12", "type": "whoassist", "position": "5", "assists": "10", "image": "https://fbref.com/req/202005121/images/headshots/b0b4fd3e_2018.jpg", "answers": ["Jack Grealish", "Darnell Furlong", "Arthur Masuaku", "Timo Werner"], "v": "17"}, {"date": "2021-05-12", "type": "whoassist", "position": "6", "assists": "9", "image": "https://fbref.com/req/202005121/images/headshots/a1d5bd30_2018.jpg", "answers": ["Marcus Rashford", "Martin \u00d8degaard", "James Justin", "Vladim\u00edr Coufal"], "v": "17"}, {"date": "2021-05-12", "type": "whoassist", "position": "7", "assists": "9", "image": "https://fbref.com/req/202005121/images/headshots/45963054_2018.jpg", "answers": ["Jamie Vardy", "Jacob Murphy", "H\u00e9ctor Beller\u00edn", "Wilfried Zaha"], "v": "17"}, {"date": "2021-05-12", "type": "whoassist", "position": "8", "assists": "8", "image": "https://fbref.com/req/202005121/images/headshots/49fe9070_2018.jpg", "answers": ["Timo Werner", "Victor Lindel\u00f6f", "Martinelli", "Phil Foden"], "v": "17"}, {"date": "2021-05-12", "type": "whoassist", "position": "9", "assists": "7", "image": "https://fbref.com/req/202005121/images/headshots/1b84dbe1_2018.jpg", "answers": ["Lucas Digne", "H\u00e9ctor Beller\u00edn", "Sadio Man\u00e9", "Conor Townsend"], "v": "17"}, {"date": "2021-05-12", "type": "whoassist", "position": "10", "assists": "7", "image": "https://fbref.com/req/202005121/images/headshots/93feac6e_2018.jpg", "answers": ["Patrick Bamford", "Lucas Moura", "James Milner", "Callum Hudson-Odoi"], "v": "17"}]